{
    "languages":[
        {
            "name":"Python",
            "url":"#",
            "imgUrl":"https://dummyimage.com/100x100/eee/444"
        },
        {
            "name":"JavaScript",
            "url":"#",
            "imgUrl":"https://dummyimage.com/100x100/eee/444"
        },
        {
            "name":"Java",
            "url":"#",
            "imgUrl":"https://dummyimage.com/100x100/eee/444"
        },
        {
            "name":"PHP",
            "url":"#",
            "imgUrl":"https://dummyimage.com/100x100/eee/444"
        },
        {
            "name":"Node.js",
            "url":"#",
            "imgUrl":"https://dummyimage.com/100x100/eee/444"
        },
        {
            "name":"Solidity",
            "url":"#",
            "imgUrl":"https://dummyimage.com/100x100/eee/444"
        }
    ],
    "backend": [
        {
            "name":"Django",
            "url":"#",
            "imgUrl":"#"
        },
        {
            "name":"Django Rest Framework",
            "url":"#",
            "imgUrl":"#"
        },
        {
            "name":"Express.js",
            "url":"#",
            "imgUrl":"#"
        },
        {
            "name":"Laravel",
            "url":"#",
            "imgUrl":"#"
        }
    ],
    "frontend": [
        {
            "name":"React.js",
            "url":"#",
            "imgUrl":"#"
        },
        {
            "name":"Redux",
            "url":"#",
            "imgUrl":"#"
        },
        {
            "name":"React Router",
            "url":"#",
            "imgUrl":"#"
        },
        {
            "name":"Tailwind CSS",
            "url":"#",
            "imgUrl":"#"
        }
    ],
    "database": [
        {
            "name":"PostgresSQL",
            "url":"#",
            "imgUrl":"#"
        },
        {
            "name":"MySQL",
            "url":"#",
            "imgUrl":"#"
        },
        {
            "name":"Redis",
            "url":"#",
            "imgUrl":"#"
        },
        {
            "name":"MongoDB",
            "url":"#",
            "imgUrl":"#"
        }
    ]
}